aws_shell-0.2.1.dist-info/DESCRIPTION.rst
aws_shell-0.2.1.dist-info/METADATA
aws_shell-0.2.1.dist-info/RECORD
aws_shell-0.2.1.dist-info/WHEEL
aws_shell-0.2.1.dist-info/entry_points.txt
aws_shell-0.2.1.dist-info/metadata.json
aws_shell-0.2.1.dist-info/top_level.txt
awsshell/__init__.py
awsshell/app.py
awsshell/autocomplete.py
awsshell/awsshellrc
awsshell/compat.py
awsshell/config.py
awsshell/db.py
awsshell/docs.py
awsshell/fuzzy.py
awsshell/keys.py
awsshell/lexer.py
awsshell/loaders.py
awsshell/makeindex.py
awsshell/shellcomplete.py
awsshell/style.py
awsshell/substring.py
awsshell/toolbar.py
awsshell/ui.py
awsshell/utils.py
awsshell/data/cloudformation/2010-05-15/completions-1.json
awsshell/data/dynamodb/2012-08-10/completions-1.json
awsshell/data/ec2/2015-04-15/completions-1.json
awsshell/data/elb/2012-06-01/completions-1.json
awsshell/data/glacier/2012-06-01/completions-1.json
awsshell/data/iam/2010-05-08/completions-1.json
awsshell/data/kinesis/2013-12-02/completions-1.json
awsshell/data/opsworks/2013-02-18/completions-1.json
awsshell/data/s3/2006-03-01/completions-1.json
awsshell/data/sns/2010-03-31/completions-1.json
awsshell/data/sqs/2012-11-05/completions-1.json
awsshell/index/__init__.py
awsshell/index/completion.py
awsshell/resource/__init__.py
awsshell/resource/index.py
